ampho/__init__.py
ampho/__main__.py
ampho/_api.py
ampho/_application.py
ampho/_bundle.py
ampho/application.py
ampho/cli.py
ampho/errors.py
ampho/main.py
ampho/signals.py
ampho/testing.py
ampho-0.4.1.dist-info/LICENSE.rst
ampho-0.4.1.dist-info/METADATA
ampho-0.4.1.dist-info/WHEEL
ampho-0.4.1.dist-info/entry_points.txt
ampho-0.4.1.dist-info/top_level.txt
ampho-0.4.1.dist-info/RECORD
